heat/__init__.py
heat/version.py
heat/api/__init__.py
heat/api/versions.py
heat/api/aws/__init__.py
heat/api/aws/ec2token.py
heat/api/aws/exception.py
heat/api/aws/utils.py
heat/api/cfn/__init__.py
heat/api/cfn/versions.py
heat/api/cfn/wsgi.py
heat/api/cfn/v1/__init__.py
heat/api/cfn/v1/signal.py
heat/api/cfn/v1/stacks.py
heat/api/middleware/__init__.py
heat/api/middleware/fault.py
heat/api/middleware/version_negotiation.py
heat/api/openstack/__init__.py
heat/api/openstack/versions.py
heat/api/openstack/wsgi.py
heat/api/openstack/v1/__init__.py
heat/api/openstack/v1/actions.py
heat/api/openstack/v1/build_info.py
heat/api/openstack/v1/events.py
heat/api/openstack/v1/resources.py
heat/api/openstack/v1/services.py
heat/api/openstack/v1/software_configs.py
heat/api/openstack/v1/software_deployments.py
heat/api/openstack/v1/stacks.py
heat/api/openstack/v1/util.py
heat/api/openstack/v1/views/__init__.py
heat/api/openstack/v1/views/stacks_view.py
heat/api/openstack/v1/views/views_common.py
heat/cloudinit/__init__.py
heat/cloudinit/boothook.sh
heat/cloudinit/config
heat/cloudinit/loguserdata.py
heat/cloudinit/part_handler.py
heat/cmd/__init__.py
heat/cmd/engine.py
heat/cmd/manage.py
heat/cmd/status.py
heat/common/__init__.py
heat/common/auth_password.py
heat/common/auth_plugin.py
heat/common/auth_url.py
heat/common/cache.py
heat/common/config.py
heat/common/context.py
heat/common/crypt.py
heat/common/custom_backend_auth.py
heat/common/endpoint_utils.py
heat/common/environment_format.py
heat/common/environment_util.py
heat/common/exception.py
heat/common/grouputils.py
heat/common/i18n.py
heat/common/identifier.py
heat/common/lifecycle_plugin_utils.py
heat/common/messaging.py
heat/common/netutils.py
heat/common/noauth.py
heat/common/param_utils.py
heat/common/password_gen.py
heat/common/plugin_loader.py
heat/common/pluginutils.py
heat/common/policy.py
heat/common/profiler.py
heat/common/serializers.py
heat/common/service_utils.py
heat/common/short_id.py
openstack_heat-25.0.0.dist-info/AUTHORS
openstack_heat-25.0.0.dist-info/LICENSE
openstack_heat-25.0.0.dist-info/METADATA
openstack_heat-25.0.0.dist-info/WHEEL
openstack_heat-25.0.0.dist-info/entry_points.txt
openstack_heat-25.0.0.dist-info/pbr.json
openstack_heat-25.0.0.dist-info/top_level.txt
openstack_heat-25.0.0.dist-info/RECORD
