Metadata-Version: 2.1
Name: openstack-heat
Version: 25.0.0
Summary: OpenStack Orchestration
Home-page: https://docs.openstack.org/heat/latest/
Author: OpenStack
Author-email: openstack-discuss@lists.openstack.org
Classifier: Environment :: OpenStack
Classifier: Intended Audience :: Information Technology
Classifier: Intended Audience :: System Administrators
Classifier: License :: OSI Approved :: Apache Software License
Classifier: Operating System :: POSIX :: Linux
Classifier: Programming Language :: Python
Classifier: Programming Language :: Python :: 3 :: Only
Classifier: Programming Language :: Python :: 3
Classifier: Programming Language :: Python :: 3.10
Classifier: Programming Language :: Python :: 3.11
Classifier: Programming Language :: Python :: 3.12
Requires-Python: >=3.10
License-File: LICENSE
License-File: AUTHORS
Requires-Dist: pbr >=3.1.1
Requires-Dist: alembic >=1.8.0
Requires-Dist: croniter >=0.3.4
Requires-Dist: cryptography >=2.5
Requires-Dist: keystoneauth1 >=3.18.0
Requires-Dist: keystonemiddleware >=5.1.0
Requires-Dist: lxml >=4.5.0
Requires-Dist: netaddr >=0.7.18
Requires-Dist: neutron-lib >=1.14.0
Requires-Dist: openstacksdk >=0.28.0
Requires-Dist: oslo.cache >=1.26.0
Requires-Dist: oslo.config >=6.8.0
Requires-Dist: oslo.concurrency >=3.26.0
Requires-Dist: oslo.context >=2.22.0
Requires-Dist: oslo.db >=6.0.0
Requires-Dist: oslo.i18n >=3.20.0
Requires-Dist: oslo.log >=4.3.0
Requires-Dist: oslo.messaging >=14.1.0
Requires-Dist: oslo.middleware >=3.31.0
Requires-Dist: oslo.policy >=4.5.0
Requires-Dist: oslo.reports >=1.18.0
Requires-Dist: oslo.serialization >=2.25.0
Requires-Dist: oslo.service[threading] >=4.2.2
Requires-Dist: oslo.upgradecheck >=1.3.0
Requires-Dist: oslo.utils >=4.5.0
Requires-Dist: osprofiler >=1.4.0
Requires-Dist: oslo.versionedobjects >=1.31.2
Requires-Dist: PasteDeploy >=1.5.0
Requires-Dist: aodhclient >=0.9.0
Requires-Dist: python-barbicanclient >=4.5.2
Requires-Dist: python-blazarclient >=1.0.1
Requires-Dist: python-cinderclient >=3.3.0
Requires-Dist: python-designateclient >=2.7.0
Requires-Dist: python-glanceclient >=2.8.0
Requires-Dist: python-heatclient >=1.10.0
Requires-Dist: python-ironicclient >=2.8.0
Requires-Dist: python-keystoneclient >=3.8.0
Requires-Dist: python-magnumclient >=2.3.0
Requires-Dist: python-manilaclient >=1.16.0
Requires-Dist: python-mistralclient >=3.1.0
Requires-Dist: python-neutronclient >=7.7.0
Requires-Dist: python-novaclient >=9.1.0
Requires-Dist: python-octaviaclient >=1.8.0
Requires-Dist: python-openstackclient >=3.12.0
Requires-Dist: python-swiftclient >=3.2.0
Requires-Dist: python-troveclient >=2.2.0
Requires-Dist: python-vitrageclient >=2.7.0
Requires-Dist: python-zaqarclient >=1.3.0
Requires-Dist: python-zunclient >=3.4.0
Requires-Dist: PyYAML >=5.1
Requires-Dist: requests >=2.23.0
Requires-Dist: tenacity >=6.1.0
Requires-Dist: tzdata >=2022.4
Requires-Dist: Routes >=2.3.1
Requires-Dist: SQLAlchemy >=1.4.0
Requires-Dist: stevedore >=3.1.0
Requires-Dist: WebOb >=1.7.1
Requires-Dist: yaql >=1.1.3
